package com.zoo.tiger;

import com.zoo.tiger.me.model.People;

import java.util.*;

public class Test {

    /**
     * jdk8
     * <p>
     * âœ  tiger git:(main) âœ— javap -c Test
     * è­¦å‘Š: äºŒè¿›åˆ¶æ–‡ä»¶TeståŒ…å«com.zoo.tiger.Test
     * Compiled from "Test.java"
     * public class com.zoo.tiger.Test {
     * public com.zoo.tiger.Test();
     * Code:
     * 0: aload_0
     * 1: invokespecial #1                  // Method java/lang/Object."<init>":()V
     * 4: return
     * <p>
     * public static void main(java.lang.String[]);
     * Code:
     * 0: ldc           #2                  // String hello
     * 2: astore_1
     * 3: ldc           #3                  // String world
     * 5: astore_2
     * 6: getstatic     #4                  // Field java/lang/System.out:Ljava/io/PrintStream;
     * 9: new           #5                  // class java/lang/StringBuilder
     * 12: dup
     * 13: invokespecial #6                  // Method java/lang/StringBuilder."<init>":()V
     * 16: aload_1
     * 17: invokevirtual #7                  // Method java/lang/StringBuilder.append:(Ljava/lang/String;)Ljava/lang/StringBuilder;
     * 20: aload_2
     * 21: invokevirtual #7                  // Method java/lang/StringBuilder.append:(Ljava/lang/String;)Ljava/lang/StringBuilder;
     * 24: invokevirtual #8                  // Method java/lang/StringBuilder.toString:()Ljava/lang/String;
     * 27: invokevirtual #9                  // Method java/io/PrintStream.println:(Ljava/lang/String;)V
     * 30: return
     * }
     * <p>
     * <p>
     * jdk20
     * <p>
     * âœ  tiger git:(main) âœ— javap -c Test
     * è­¦å‘Š: æ–‡ä»¶ ./Test.class ä¸åŒ…å«ç±» Test
     * Compiled from "Test.java"
     * public class com.zoo.tiger.Test {
     * public com.zoo.tiger.Test();
     * Code:
     * 0: aload_0
     * 1: invokespecial #1                  // Method java/lang/Object."<init>":()V
     * 4: return
     * <p>
     * public static void main(java.lang.String[]);
     * Code:
     * 0: ldc           #7                  // String hello
     * 2: astore_1
     * 3: ldc           #9                  // String world
     * 5: astore_2
     * 6: getstatic     #11                 // Field java/lang/System.out:Ljava/io/PrintStream;
     * 9: aload_1
     * 10: aload_2
     * 11: invokedynamic #17,  0             // InvokeDynamic #0:makeConcatWithConstants:(Ljava/lang/String;Ljava/lang/String;)Ljava/lang/String;
     * 16: invokevirtual #21                 // Method java/io/PrintStream.println:(Ljava/lang/String;)V
     * 19: return
     * }
     * <p>
     * conclusion
     * <p>
     * åœ¨ JDK 8 ä¸­ï¼Œå­—ç¬¦ä¸²è¿æ¥æ“ä½œç¬¦ï¼ˆ+ï¼‰çš„å®ç°ä½¿ç”¨äº† StringBuilderï¼Œè€Œåœ¨ JDK 11 ä¸­ï¼Œå­—ç¬¦ä¸²è¿æ¥æ“ä½œç¬¦ï¼ˆ+ï¼‰çš„å®ç°ä¼˜åŒ–ä¸ºä½¿ç”¨äº† invokedynamic æŒ‡ä»¤ï¼Œè¿™å¯ä»¥å¸¦æ¥æ›´å¥½çš„æ€§èƒ½ã€‚
     * <p>
     * åœ¨ JDK 8 ä¸­ï¼Œå½“ä½¿ç”¨å­—ç¬¦ä¸²è¿æ¥æ“ä½œç¬¦ï¼ˆ+ï¼‰è¿æ¥ä¸¤ä¸ªå­—ç¬¦ä¸²æ—¶ï¼Œç¼–è¯‘å™¨å°†å…¶è½¬æ¢ä¸ºå¦‚ä¸‹ä»£ç ï¼š
     * <p>
     * arduino
     * Copy code
     * String str1 = "Hello";
     * String str2 = "world";
     * String result = new StringBuilder(str1).append(str2).toString();
     * åœ¨ä¸Šé¢çš„ä»£ç ä¸­ï¼Œå­—ç¬¦ä¸²è¿æ¥æ“ä½œç¬¦ï¼ˆ+ï¼‰ä¼šåˆ›å»ºä¸€ä¸ª StringBuilder å¯¹è±¡ï¼Œå¹¶ä½¿ç”¨ append() æ–¹æ³•å°†ä¸¤ä¸ªå­—ç¬¦ä¸²è¿æ¥èµ·æ¥ã€‚æœ€åï¼Œè°ƒç”¨ toString() æ–¹æ³•å°† StringBuilder å¯¹è±¡è½¬æ¢ä¸º String å¯¹è±¡ã€‚
     * <p>
     * åœ¨ JDK 11 ä¸­ï¼Œå­—ç¬¦ä¸²è¿æ¥æ“ä½œç¬¦ï¼ˆ+ï¼‰çš„å®ç°ä½¿ç”¨ invokedynamic æŒ‡ä»¤ï¼Œè¿™å¯ä»¥å¸¦æ¥æ›´å¥½çš„æ€§èƒ½ã€‚invokedynamic æŒ‡ä»¤å¯ä»¥åŠ¨æ€åœ°è§£ææ–¹æ³•è°ƒç”¨ï¼Œè¿™æ„å‘³ç€å®ƒå¯ä»¥æ ¹æ®è¿è¡Œæ—¶çš„ç±»å‹æ¥é€‰æ‹©æœ€ä¼˜çš„å®ç°æ–¹å¼ã€‚åœ¨ JDK 11 ä¸­ï¼Œå½“ä½¿ç”¨å­—ç¬¦ä¸²è¿æ¥æ“ä½œç¬¦ï¼ˆ+ï¼‰è¿æ¥ä¸¤ä¸ªå­—ç¬¦ä¸²æ—¶ï¼Œç¼–è¯‘å™¨å°†å…¶è½¬æ¢ä¸ºå¦‚ä¸‹ä»£ç ï¼š
     * <p>
     * arduino
     * Copy code
     * String str1 = "Hello";
     * String str2 = "world";
     * String result = StringConcatFactory.makeConcat(str1, str2).toString();
     * åœ¨ä¸Šé¢çš„ä»£ç ä¸­ï¼ŒStringConcatFactory.makeConcat() æ–¹æ³•è¿”å›ä¸€ä¸ª StringConcatFactory çš„å®ä¾‹ï¼Œè¯¥å®ä¾‹æ ¹æ®è¿è¡Œæ—¶çš„ç±»å‹æ¥é€‰æ‹©æœ€ä¼˜çš„å®ç°æ–¹å¼ï¼Œä»¥è¾¾åˆ°æ›´å¥½çš„æ€§èƒ½ã€‚
     * <p>
     * å› æ­¤ï¼ŒJDK 11 ä¸­å­—ç¬¦ä¸²è¿æ¥æ“ä½œç¬¦ï¼ˆ+ï¼‰çš„å®ç°æ¯” JDK 8 æ›´åŠ é«˜æ•ˆã€‚
     *
     * @param args
     */
    public static void main(String[] args) {

        String a = "hello";

        String b = "world";

        System.out.println(a + b);

        String c = "1";

        System.out.println(c.hashCode());


        HashMap<Object, Object> objectObjectHashMap = new HashMap<>(15);
        // åˆå§‹åŒ–çš„æ—¶å€™thresholdæ˜¯åˆå§‹å®¹é‡ï¼Œå¯ä»¥çœ‹ä¸‹HashMapçš„æºç å®šä¹‰thresholdçš„æ—¶å€™çš„è‹±æ–‡æ³¨é‡Š
        //    /**
        //     * The next size value at which to resize (capacity * load factor).
        //     *
        //     * @serial
        //     */
        //    // (The javadoc description is true upon serialization.
        //    // Additionally, if the table array has not been allocated, this
        //    // field holds the initial array capacity, or zero signifying
        //    // DEFAULT_INITIAL_CAPACITY.)
        //    int threshold;

        // new ä¸€ä¸ªhashmapçš„æ—¶å€™ å†…éƒ¨çš„tableæ˜¯ç©ºçš„å•Šï¼Œæ‰€ä»¥putå€¼çš„æ—¶å€™ä¼šå…ˆresize() ç„¶åèµ‹å€¼çœŸæ­£çš„capacityå’Œthreshold
        objectObjectHashMap.put("a",1);

        // ç¤ºä¾‹ -Xms20m -Xmx20m -XX:+HeapDumpOnOutOfMemoryError
        // å®é™… -Xms2m -Xmx2m -XX:+PrintHeapAtGC  å †æº¢å‡º
        // Exception in thread "main" java.lang.OutOfMemoryError: Java heap space
        //	at java.util.Arrays.copyOf(Arrays.java:3210)
        /*List<People> list = new ArrayList<>();
        while (true) {
            list.add(new People(1,"a"));
        }*/

//        -Xss128k -XX:+HeapDumpOnOutOfMemoryError


        // å¸¸é‡æ± æº¢å‡º  VM Argsï¼š-XX:PermSize=6M -XX:MaxPermSize=6M
        // ä½¿ç”¨Setä¿æŒç€å¸¸é‡æ± å¼•ç”¨ï¼Œé¿å…Full GCå›æ”¶å¸¸é‡æ± è¡Œä¸º???è¿™é‡Œæ˜¯1.6çš„ä¾‹å­
        /*Set<String> set = new HashSet<String>();
        // åœ¨shortèŒƒå›´å†…è¶³ä»¥è®©6MBçš„PermSizeäº§ç”ŸOOMäº†
        short i = 0;
        while (true) {
            set.add(String.valueOf(i++).intern());
        }*/

        // ä¸‹é¢è¿™ç§åº”è¯¥æ˜¯ä¼šå›æ”¶æ‰jdk1.8 æ²¡æœ‰æº¢å‡ºçš„æƒ…å†µ
        /*int j = 1;
        Set<String> set = new HashSet<String>();
        while (true) {
            String.valueOf(j).intern();
//            set.add(intern);
            j ++;
//            System.out.println(abc);
        }*/

        /*String s1 = new String("Java");
        String s2 = s1.intern();
        System.out.println("s1 == s2:" + s1 == s2);//false
        String s3 = "Java";
        System.out.println(s2 == s3);
        System.out.println(s2 == s3);
        // è¿™é‡ŒæŒ‰ç…§ è¿ç®—ç¬¦çš„é¡ºåºä¼šå…ˆè®¡ç®—å‰é¢çš„å­—ç¬¦ä¸²ç›¸åŠ  == s3 ğŸ˜­
        System.out.println("s2 == s3" + s2 == s3); // false
        System.out.println("s2 == s3" + (s2 == s3));// s2 == s3true


        String s4 = "abccc";
        String s5 = "abccc";
        String s6 = new String("abccc");
        System.out.println(s4 == s5);//true
        System.out.println(s4 == s6);//false

        String s7 = new String("Java");
        System.out.println(s1 == s7);// false*/

//        æµ…å…‹éš†
        People[]  o1  =  {new  People(1,  "Java")};
        People[]  o2  =  Arrays.copyOf(o1,  o1.length);
        //  ä¿®æ”¹åŸå‹å¯¹è±¡çš„ç¬¬ä¸€ä¸ªå…ƒç´ çš„å€¼
        o1[0].setName("Jdk");
        System.out.println("o1:"  +  o1[0].getName());
        System.out.println("o2:"  +  o2[0].getName());

    }


}
